rsksymplexmethod/__init__.py
rsksymplexmethod/dual.py
rsksymplexmethod/initial.py
rsksymplexmethod/main.py
rsksymplexmethod/symplex.py
rsksymplexmethod/utils.py
rsksymplexmethod-0.1.dist-info/LICENSE.txt
rsksymplexmethod-0.1.dist-info/METADATA
rsksymplexmethod-0.1.dist-info/WHEEL
rsksymplexmethod-0.1.dist-info/top_level.txt
rsksymplexmethod-0.1.dist-info/RECORD
