Metadata-Version: 2.1
Name: rsksymplexmethod
Version: 0.1
Summary: Simplex method by rasteeslove.
Home-page: https://github.com/rasteeslove/rsksymplexmethod
Download-URL: https://github.com/rasteeslove/rsksymplexmethod/archive/refs/tags/v_01.tar.gz
Author: Rostislav Kayko
Author-email: krastsislau@gmail.com
License: MIT
Keywords: Math,Simplex,Method
Classifier: Development Status :: 3 - Alpha
Classifier: Intended Audience :: Developers
Classifier: Topic :: Software Development :: Build Tools
Classifier: License :: OSI Approved :: MIT License
Classifier: Programming Language :: Python :: 3
Classifier: Programming Language :: Python :: 3.4
Classifier: Programming Language :: Python :: 3.5
Classifier: Programming Language :: Python :: 3.6
Classifier: Programming Language :: Python :: 3.10
License-File: LICENSE.txt
Requires-Dist: numpy
Requires-Dist: scipy
